{
  "builds": [
    {
      "builderid": 160,
      "buildid": 168400,
      "buildrequestid": 1930147,
      "complete": true,
      "complete_at": 1631130124,
      "masterid": 1,
      "number": 1,
      "properties": {},
      "results": 6,
      "started_at": 1631121003,
      "state_string": "cancelled build (cancelled)",
      "workerid": 121
    },
    {
      "builderid": 160,
      "buildid": 168426,
      "buildrequestid": 1930190,
      "complete": true,
      "complete_at": 1631133988,
      "masterid": 1,
      "number": 2,
      "properties": {},
      "results": 2,
      "started_at": 1631130635,
      "state_string": "build (failure)",
      "workerid": 121
    },
    {
      "builderid": 160,
      "buildid": 169027,
      "buildrequestid": 1960556,
      "complete": true,
      "complete_at": 1631181074,
      "masterid": 1,
      "number": 8,
      "properties": {},
      "results": 0,
      "started_at": 1631175900,
      "state_string": "build successful",
      "workerid": 121
    },
    {
      "builderid": 160,
      "buildid": 169663,
      "buildrequestid": 1966712,
      "complete": true,
      "complete_at": 1631233076,
      "masterid": 1,
      "number": 13,
      "properties": {},
      "results": 0,
      "started_at": 1631223850,
      "state_string": "build successful",
      "workerid": 121
    },
    {
      "builderid": 160,
      "buildid": 168471,
      "buildrequestid": 1953580,
      "complete": true,
      "complete_at": 1631149167,
      "masterid": 1,
      "number": 3,
      "properties": {},
      "results": 0,
      "started_at": 1631134864,
      "state_string": "build successful",
      "workerid": 121
    },
    {
      "builderid": 160,
      "buildid": 169855,
      "buildrequestid": 1967661,
      "complete": true,
      "complete_at": 1631252011,
      "masterid": 1,
      "number": 15,
      "properties": {},
      "results": 0,
      "started_at": 1631242124,
      "state_string": "build successful",
      "workerid": 121
    },
    {
      "builderid": 160,
      "buildid": 169758,
      "buildrequestid": 1967339,
      "complete": true,
      "complete_at": 1631242124,
      "masterid": 1,
      "number": 14,
      "properties": {},
      "results": 0,
      "started_at": 1631233075,
      "state_string": "build successful",
      "workerid": 121
    },
    {
      "builderid": 160,
      "buildid": 169519,
      "buildrequestid": 1964622,
      "complete": true,
      "complete_at": 1631223850,
      "masterid": 1,
      "number": 12,
      "properties": {},
      "results": 0,
      "started_at": 1631213359,
      "state_string": "build successful",
      "workerid": 121
    },
    {
      "builderid": 160,
      "buildid": 168877,
      "buildrequestid": 1959849,
      "complete": true,
      "complete_at": 1631172312,
      "masterid": 1,
      "number": 6,
      "properties": {},
      "results": 0,
      "started_at": 1631165362,
      "state_string": "build successful",
      "workerid": 121
    },
    {
      "builderid": 160,
      "buildid": 168815,
      "buildrequestid": 1959717,
      "complete": true,
      "complete_at": 1631165362,
      "masterid": 1,
      "number": 5,
      "properties": {},
      "results": 0,
      "started_at": 1631160698,
      "state_string": "build successful",
      "workerid": 121
    },
    {
      "builderid": 160,
      "buildid": 170053,
      "buildrequestid": 1968423,
      "complete": true,
      "complete_at": 1631273684,
      "masterid": 1,
      "number": 17,
      "properties": {},
      "results": 0,
      "started_at": 1631263290,
      "state_string": "build successful",
      "workerid": 121
    },
    {
      "builderid": 160,
      "buildid": 168685,
      "buildrequestid": 1958004,
      "complete": true,
      "complete_at": 1631160698,
      "masterid": 1,
      "number": 4,
      "properties": {},
      "results": 0,
      "started_at": 1631149167,
      "state_string": "build successful",
      "workerid": 121
    },
    {
      "builderid": 160,
      "buildid": 169103,
      "buildrequestid": 1960982,
      "complete": true,
      "complete_at": 1631190792,
      "masterid": 1,
      "number": 9,
      "properties": {},
      "results": 0,
      "started_at": 1631181074,
      "state_string": "build successful",
      "workerid": 121
    },
    {
      "builderid": 160,
      "buildid": 169340,
      "buildrequestid": 1962926,
      "complete": true,
      "complete_at": 1631213359,
      "masterid": 1,
      "number": 11,
      "properties": {},
      "results": 0,
      "started_at": 1631200324,
      "state_string": "build successful",
      "workerid": 121
    },
    {
      "builderid": 160,
      "buildid": 169957,
      "buildrequestid": 1967940,
      "complete": true,
      "complete_at": 1631263291,
      "masterid": 1,
      "number": 16,
      "properties": {},
      "results": 0,
      "started_at": 1631252010,
      "state_string": "build successful",
      "workerid": 121
    },
    {
      "builderid": 160,
      "buildid": 169234,
      "buildrequestid": 1961403,
      "complete": true,
      "complete_at": 1631200324,
      "masterid": 1,
      "number": 10,
      "properties": {},
      "results": 0,
      "started_at": 1631190791,
      "state_string": "build successful",
      "workerid": 121
    },
    {
      "builderid": 160,
      "buildid": 168980,
      "buildrequestid": 1960483,
      "complete": true,
      "complete_at": 1631175900,
      "masterid": 1,
      "number": 7,
      "properties": {},
      "results": 2,
      "started_at": 1631172311,
      "state_string": "failed build (failure)",
      "workerid": 121
    },
    {
      "builderid": 160,
      "buildid": 170192,
      "buildrequestid": 1970500,
      "complete": true,
      "complete_at": 1631286424,
      "masterid": 1,
      "number": 18,
      "properties": {},
      "results": 0,
      "started_at": 1631273683,
      "state_string": "build successful",
      "workerid": 121
    },
    {
      "builderid": 160,
      "buildid": 170357,
      "buildrequestid": 1972409,
      "complete": true,
      "complete_at": 1631297071,
      "masterid": 1,
      "number": 19,
      "properties": {},
      "results": 0,
      "started_at": 1631286424,
      "state_string": "build successful",
      "workerid": 121
    },
    {
      "builderid": 160,
      "buildid": 170507,
      "buildrequestid": 1974600,
      "complete": true,
      "complete_at": 1631306541,
      "masterid": 1,
      "number": 20,
      "properties": {},
      "results": 0,
      "started_at": 1631297070,
      "state_string": "build successful",
      "workerid": 121
    },
    {
      "builderid": 160,
      "buildid": 170674,
      "buildrequestid": 1976317,
      "complete": true,
      "complete_at": 1631317367,
      "masterid": 1,
      "number": 21,
      "properties": {},
      "results": 0,
      "started_at": 1631306541,
      "state_string": "build successful",
      "workerid": 121
    },
    {
      "builderid": 160,
      "buildid": 170769,
      "buildrequestid": 1976693,
      "complete": true,
      "complete_at": 1631327458,
      "masterid": 1,
      "number": 22,
      "properties": {},
      "results": 0,
      "started_at": 1631317367,
      "state_string": "build successful",
      "workerid": 121
    },
    {
      "builderid": 160,
      "buildid": 170884,
      "buildrequestid": 1977736,
      "complete": true,
      "complete_at": 1631335098,
      "masterid": 1,
      "number": 23,
      "properties": {},
      "results": 0,
      "started_at": 1631327458,
      "state_string": "build successful",
      "workerid": 121
    },
    {
      "builderid": 160,
      "buildid": 170936,
      "buildrequestid": 1977932,
      "complete": true,
      "complete_at": 1631340398,
      "masterid": 1,
      "number": 24,
      "properties": {},
      "results": 0,
      "started_at": 1631335098,
      "state_string": "build successful",
      "workerid": 121
    },
    {
      "builderid": 160,
      "buildid": 171059,
      "buildrequestid": 1978376,
      "complete": true,
      "complete_at": 1631357453,
      "masterid": 1,
      "number": 26,
      "properties": {},
      "results": 0,
      "started_at": 1631351294,
      "state_string": "build successful",
      "workerid": 121
    },
    {
      "builderid": 160,
      "buildid": 171013,
      "buildrequestid": 1978090,
      "complete": true,
      "complete_at": 1631351294,
      "masterid": 1,
      "number": 25,
      "properties": {},
      "results": 2,
      "started_at": 1631348561,
      "state_string": "failed build (failure)",
      "workerid": 121
    },
    {
      "builderid": 160,
      "buildid": 171116,
      "buildrequestid": 1978505,
      "complete": true,
      "complete_at": 1631365471,
      "masterid": 1,
      "number": 27,
      "properties": {},
      "results": 0,
      "started_at": 1631357547,
      "state_string": "build successful",
      "workerid": 121
    },
    {
      "builderid": 160,
      "buildid": 171154,
      "buildrequestid": 1979218,
      "complete": true,
      "complete_at": 1631374474,
      "masterid": 1,
      "number": 28,
      "properties": {},
      "results": 0,
      "started_at": 1631365471,
      "state_string": "build successful",
      "workerid": 121
    },
    {
      "builderid": 160,
      "buildid": 171279,
      "buildrequestid": 1979924,
      "complete": true,
      "complete_at": 1631389410,
      "masterid": 1,
      "number": 30,
      "properties": {},
      "results": 0,
      "started_at": 1631382839,
      "state_string": "build successful",
      "workerid": 121
    },
    {
      "builderid": 160,
      "buildid": 171235,
      "buildrequestid": 1979735,
      "complete": true,
      "complete_at": 1631382839,
      "masterid": 1,
      "number": 29,
      "properties": {},
      "results": 0,
      "started_at": 1631374474,
      "state_string": "build successful",
      "workerid": 121
    },
    {
      "builderid": 160,
      "buildid": 171333,
      "buildrequestid": 1980422,
      "complete": true,
      "complete_at": 1631397515,
      "masterid": 1,
      "number": 31,
      "properties": {},
      "results": 0,
      "started_at": 1631389410,
      "state_string": "build successful",
      "workerid": 121
    },
    {
      "builderid": 160,
      "buildid": 171381,
      "buildrequestid": 1980549,
      "complete": true,
      "complete_at": 1631429777,
      "masterid": 1,
      "number": 32,
      "properties": {},
      "results": 0,
      "started_at": 1631421278,
      "state_string": "build successful",
      "workerid": 121
    },
    {
      "builderid": 160,
      "buildid": 171455,
      "buildrequestid": 1981059,
      "complete": true,
      "complete_at": 1631437585,
      "masterid": 1,
      "number": 33,
      "properties": {},
      "results": 0,
      "started_at": 1631429777,
      "state_string": "build successful",
      "workerid": 121
    },
    {
      "builderid": 160,
      "buildid": 171512,
      "buildrequestid": 1981359,
      "complete": true,
      "complete_at": 1631444514,
      "masterid": 1,
      "number": 34,
      "properties": {},
      "results": 0,
      "started_at": 1631437585,
      "state_string": "build successful",
      "workerid": 121
    },
    {
      "builderid": 160,
      "buildid": 171535,
      "buildrequestid": 1981773,
      "complete": true,
      "complete_at": 1631451770,
      "masterid": 1,
      "number": 35,
      "properties": {},
      "results": 0,
      "started_at": 1631444513,
      "state_string": "build successful",
      "workerid": 121
    },
    {
      "builderid": 160,
      "buildid": 171582,
      "buildrequestid": 1981963,
      "complete": true,
      "complete_at": 1631460583,
      "masterid": 1,
      "number": 36,
      "properties": {},
      "results": 0,
      "started_at": 1631451770,
      "state_string": "build successful",
      "workerid": 121
    },
    {
      "builderid": 160,
      "buildid": 171637,
      "buildrequestid": 1982242,
      "complete": true,
      "complete_at": 1631470290,
      "masterid": 1,
      "number": 37,
      "properties": {},
      "results": 0,
      "started_at": 1631460582,
      "state_string": "build successful",
      "workerid": 121
    },
    {
      "builderid": 160,
      "buildid": 171688,
      "buildrequestid": 1982485,
      "complete": true,
      "complete_at": 1631477178,
      "masterid": 1,
      "number": 38,
      "properties": {},
      "results": 0,
      "started_at": 1631470290,
      "state_string": "build successful",
      "workerid": 121
    },
    {
      "builderid": 160,
      "buildid": 171727,
      "buildrequestid": 1982649,
      "complete": true,
      "complete_at": 1631494052,
      "masterid": 1,
      "number": 39,
      "properties": {},
      "results": 0,
      "started_at": 1631484641,
      "state_string": "build successful",
      "workerid": 121
    },
    {
      "builderid": 160,
      "buildid": 171817,
      "buildrequestid": 1983246,
      "complete": true,
      "complete_at": 1631502722,
      "masterid": 1,
      "number": 40,
      "properties": {},
      "results": 0,
      "started_at": 1631494123,
      "state_string": "build successful",
      "workerid": 121
    },
    {
      "builderid": 160,
      "buildid": 171859,
      "buildrequestid": 1983443,
      "complete": true,
      "complete_at": 1631512249,
      "masterid": 1,
      "number": 41,
      "properties": {},
      "results": 0,
      "started_at": 1631502722,
      "state_string": "build successful",
      "workerid": 121
    },
    {
      "builderid": 160,
      "buildid": 171951,
      "buildrequestid": 1983923,
      "complete": true,
      "complete_at": 1631521706,
      "masterid": 1,
      "number": 42,
      "properties": {},
      "results": 0,
      "started_at": 1631512248,
      "state_string": "build successful",
      "workerid": 121
    },
    {
      "builderid": 160,
      "buildid": 172033,
      "buildrequestid": 1984107,
      "complete": true,
      "complete_at": 1631528341,
      "masterid": 1,
      "number": 43,
      "properties": {},
      "results": 0,
      "started_at": 1631521706,
      "state_string": "build successful",
      "workerid": 121
    },
    {
      "builderid": 160,
      "buildid": 172149,
      "buildrequestid": 1986801,
      "complete": true,
      "complete_at": 1631540056,
      "masterid": 1,
      "number": 44,
      "properties": {},
      "results": 0,
      "started_at": 1631528409,
      "state_string": "build successful",
      "workerid": 121
    },
    {
      "builderid": 160,
      "buildid": 172376,
      "buildrequestid": 1989155,
      "complete": true,
      "complete_at": 1631557566,
      "masterid": 1,
      "number": 46,
      "properties": {},
      "results": 0,
      "started_at": 1631545868,
      "state_string": "build successful",
      "workerid": 121
    },
    {
      "builderid": 160,
      "buildid": 172331,
      "buildrequestid": 1987473,
      "complete": true,
      "complete_at": 1631545868,
      "masterid": 1,
      "number": 45,
      "properties": {},
      "results": 0,
      "started_at": 1631540055,
      "state_string": "build successful",
      "workerid": 121
    },
    {
      "builderid": 160,
      "buildid": 172499,
      "buildrequestid": 1990441,
      "complete": true,
      "complete_at": 1631569743,
      "masterid": 1,
      "number": 47,
      "properties": {},
      "results": 0,
      "started_at": 1631557566,
      "state_string": "build successful",
      "workerid": 121
    },
    {
      "builderid": 160,
      "buildid": 172595,
      "buildrequestid": 1991431,
      "complete": true,
      "complete_at": 1631582858,
      "masterid": 1,
      "number": 48,
      "properties": {},
      "results": 0,
      "started_at": 1631569743,
      "state_string": "build successful",
      "workerid": 121
    },
    {
      "builderid": 160,
      "buildid": 172767,
      "buildrequestid": 1992994,
      "complete": true,
      "complete_at": 1631599136,
      "masterid": 1,
      "number": 50,
      "properties": {},
      "results": 0,
      "started_at": 1631588818,
      "state_string": "build successful",
      "workerid": 121
    },
    {
      "builderid": 160,
      "buildid": 172741,
      "buildrequestid": 1992371,
      "complete": true,
      "complete_at": 1631588819,
      "masterid": 1,
      "number": 49,
      "properties": {},
      "results": 0,
      "started_at": 1631582857,
      "state_string": "build successful",
      "workerid": 121
    },
    {
      "builderid": 160,
      "buildid": 172830,
      "buildrequestid": 1993409,
      "complete": true,
      "complete_at": 1631606588,
      "masterid": 1,
      "number": 51,
      "properties": {},
      "results": 0,
      "started_at": 1631599135,
      "state_string": "build successful",
      "workerid": 121
    },
    {
      "builderid": 160,
      "buildid": 172890,
      "buildrequestid": 1994090,
      "complete": true,
      "complete_at": 1631616821,
      "masterid": 1,
      "number": 52,
      "properties": {},
      "results": 0,
      "started_at": 1631606587,
      "state_string": "build successful",
      "workerid": 121
    },
    {
      "builderid": 160,
      "buildid": 173003,
      "buildrequestid": 1995384,
      "complete": true,
      "complete_at": 1631625502,
      "masterid": 1,
      "number": 53,
      "properties": {},
      "results": 0,
      "started_at": 1631616821,
      "state_string": "build successful",
      "workerid": 121
    },
    {
      "builderid": 160,
      "buildid": 173063,
      "buildrequestid": 1995774,
      "complete": true,
      "complete_at": 1631635034,
      "masterid": 1,
      "number": 54,
      "properties": {},
      "results": 0,
      "started_at": 1631625501,
      "state_string": "build successful",
      "workerid": 121
    },
    {
      "builderid": 160,
      "buildid": 173169,
      "buildrequestid": 1997087,
      "complete": true,
      "complete_at": 1631646101,
      "masterid": 1,
      "number": 55,
      "properties": {},
      "results": 0,
      "started_at": 1631635034,
      "state_string": "build successful",
      "workerid": 121
    },
    {
      "builderid": 160,
      "buildid": 173266,
      "buildrequestid": 1998090,
      "complete": true,
      "complete_at": 1631657288,
      "masterid": 1,
      "number": 56,
      "properties": {},
      "results": 0,
      "started_at": 1631646101,
      "state_string": "build successful",
      "workerid": 121
    },
    {
      "builderid": 160,
      "buildid": 173389,
      "buildrequestid": 1998818,
      "complete": true,
      "complete_at": 1631666183,
      "masterid": 1,
      "number": 57,
      "properties": {},
      "results": 0,
      "started_at": 1631657287,
      "state_string": "build successful",
      "workerid": 121
    },
    {
      "builderid": 160,
      "buildid": 173466,
      "buildrequestid": 2000244,
      "complete": true,
      "complete_at": 1631676638,
      "masterid": 1,
      "number": 58,
      "properties": {},
      "results": 0,
      "started_at": 1631666183,
      "state_string": "build successful",
      "workerid": 121
    },
    {
      "builderid": 160,
      "buildid": 173563,
      "buildrequestid": 2001071,
      "complete": true,
      "complete_at": 1631683147,
      "masterid": 1,
      "number": 59,
      "properties": {},
      "results": 0,
      "started_at": 1631676638,
      "state_string": "build successful",
      "workerid": 121
    },
    {
      "builderid": 160,
      "buildid": 173600,
      "buildrequestid": 2001322,
      "complete": true,
      "complete_at": 1631692182,
      "masterid": 1,
      "number": 60,
      "properties": {},
      "results": 0,
      "started_at": 1631683248,
      "state_string": "build successful",
      "workerid": 121
    },
    {
      "builderid": 160,
      "buildid": 173667,
      "buildrequestid": 2001775,
      "complete": true,
      "complete_at": 1631703217,
      "masterid": 1,
      "number": 61,
      "properties": {},
      "results": 0,
      "started_at": 1631692182,
      "state_string": "build successful",
      "workerid": 121
    },
    {
      "builderid": 160,
      "buildid": 173817,
      "buildrequestid": 2003128,
      "complete": true,
      "complete_at": 1631713126,
      "masterid": 1,
      "number": 62,
      "properties": {},
      "results": 0,
      "started_at": 1631703217,
      "state_string": "build successful",
      "workerid": 121
    },
    {
      "builderid": 160,
      "buildid": 173913,
      "buildrequestid": 2003794,
      "complete": true,
      "complete_at": 1631722139,
      "masterid": 1,
      "number": 63,
      "properties": {},
      "results": 0,
      "started_at": 1631713126,
      "state_string": "build successful",
      "workerid": 121
    },
    {
      "builderid": 160,
      "buildid": 173996,
      "buildrequestid": 2004476,
      "complete": true,
      "complete_at": 1631730866,
      "masterid": 1,
      "number": 64,
      "properties": {},
      "results": 0,
      "started_at": 1631722210,
      "state_string": "build successful",
      "workerid": 121
    },
    {
      "builderid": 160,
      "buildid": 174078,
      "buildrequestid": 2004847,
      "complete": true,
      "complete_at": 1631738382,
      "masterid": 1,
      "number": 65,
      "properties": {},
      "results": 6,
      "started_at": 1631730865,
      "state_string": "cancelled build (cancelled)",
      "workerid": 121
    },
    {
      "builderid": 160,
      "buildid": 174152,
      "buildrequestid": 2006066,
      "complete": true,
      "complete_at": 1631747338,
      "masterid": 1,
      "number": 66,
      "properties": {},
      "results": 0,
      "started_at": 1631738852,
      "state_string": "build successful",
      "workerid": 121
    },
    {
      "builderid": 160,
      "buildid": 174187,
      "buildrequestid": 2008816,
      "complete": true,
      "complete_at": 1631839498,
      "masterid": 1,
      "number": 67,
      "properties": {},
      "results": 0,
      "started_at": 1631829265,
      "state_string": "build successful",
      "workerid": 121
    },
    {
      "builderid": 160,
      "buildid": 174305,
      "buildrequestid": 2017479,
      "complete": true,
      "complete_at": 1631846558,
      "masterid": 1,
      "number": 68,
      "properties": {},
      "results": 0,
      "started_at": 1631839498,
      "state_string": "build successful",
      "workerid": 121
    },
    {
      "builderid": 160,
      "buildid": 174385,
      "buildrequestid": 2017707,
      "complete": true,
      "complete_at": 1631852564,
      "masterid": 1,
      "number": 69,
      "properties": {},
      "results": 0,
      "started_at": 1631846557,
      "state_string": "build successful",
      "workerid": 121
    },
    {
      "builderid": 160,
      "buildid": 174520,
      "buildrequestid": 2018474,
      "complete": true,
      "complete_at": 1631863103,
      "masterid": 1,
      "number": 71,
      "properties": {},
      "results": 0,
      "started_at": 1631857554,
      "state_string": "build successful",
      "workerid": 121
    },
    {
      "builderid": 160,
      "buildid": 174479,
      "buildrequestid": 2018311,
      "complete": true,
      "complete_at": 1631857555,
      "masterid": 1,
      "number": 70,
      "properties": {},
      "results": 0,
      "started_at": 1631852563,
      "state_string": "build successful",
      "workerid": 121
    },
    {
      "builderid": 160,
      "buildid": 174576,
      "buildrequestid": 2018720,
      "complete": true,
      "complete_at": 1631874151,
      "masterid": 1,
      "number": 72,
      "properties": {},
      "results": 0,
      "started_at": 1631863102,
      "state_string": "build successful",
      "workerid": 121
    },
    {
      "builderid": 160,
      "buildid": 174734,
      "buildrequestid": 2019990,
      "complete": true,
      "complete_at": 1631883050,
      "masterid": 1,
      "number": 73,
      "properties": {},
      "results": 0,
      "started_at": 1631874150,
      "state_string": "build successful",
      "workerid": 121
    },
    {
      "builderid": 160,
      "buildid": 174815,
      "buildrequestid": 2020860,
      "complete": true,
      "complete_at": 1631895465,
      "masterid": 1,
      "number": 74,
      "properties": {},
      "results": 0,
      "started_at": 1631883049,
      "state_string": "build successful",
      "workerid": 121
    },
    {
      "builderid": 160,
      "buildid": 174954,
      "buildrequestid": 2022719,
      "complete": true,
      "complete_at": 1631905318,
      "masterid": 1,
      "number": 75,
      "properties": {},
      "results": 0,
      "started_at": 1631895474,
      "state_string": "build successful",
      "workerid": 121
    },
    {
      "builderid": 160,
      "buildid": 175035,
      "buildrequestid": 2023390,
      "complete": true,
      "complete_at": 1631916159,
      "masterid": 1,
      "number": 76,
      "properties": {},
      "results": 0,
      "started_at": 1631905317,
      "state_string": "build successful",
      "workerid": 121
    },
    {
      "builderid": 160,
      "buildid": 175167,
      "buildrequestid": 2023834,
      "complete": true,
      "complete_at": 1631927678,
      "masterid": 1,
      "number": 77,
      "properties": {},
      "results": 0,
      "started_at": 1631916295,
      "state_string": "build successful",
      "workerid": 121
    },
    {
      "builderid": 160,
      "buildid": 175278,
      "buildrequestid": 2026045,
      "complete": true,
      "complete_at": 1631943861,
      "masterid": 1,
      "number": 79,
      "properties": {},
      "results": 0,
      "started_at": 1631935412,
      "state_string": "build successful",
      "workerid": 121
    },
    {
      "builderid": 160,
      "buildid": 175241,
      "buildrequestid": 2025840,
      "complete": true,
      "complete_at": 1631935412,
      "masterid": 1,
      "number": 78,
      "properties": {},
      "results": 0,
      "started_at": 1631927678,
      "state_string": "build successful",
      "workerid": 121
    },
    {
      "builderid": 160,
      "buildid": 175309,
      "buildrequestid": 2026231,
      "complete": true,
      "complete_at": 1631959642,
      "masterid": 1,
      "number": 81,
      "properties": {},
      "results": 0,
      "started_at": 1631951412,
      "state_string": "build successful",
      "workerid": 121
    },
    {
      "builderid": 160,
      "buildid": 175295,
      "buildrequestid": 2026147,
      "complete": true,
      "complete_at": 1631951412,
      "masterid": 1,
      "number": 80,
      "properties": {},
      "results": 0,
      "started_at": 1631943860,
      "state_string": "build successful",
      "workerid": 121
    },
    {
      "builderid": 160,
      "buildid": 175337,
      "buildrequestid": 2026350,
      "complete": true,
      "complete_at": 1631967811,
      "masterid": 1,
      "number": 82,
      "properties": {},
      "results": 0,
      "started_at": 1631959642,
      "state_string": "build successful",
      "workerid": 121
    },
    {
      "builderid": 160,
      "buildid": 175423,
      "buildrequestid": 2027019,
      "complete": true,
      "complete_at": 1631984996,
      "masterid": 1,
      "number": 84,
      "properties": {},
      "results": 0,
      "started_at": 1631977207,
      "state_string": "build successful",
      "workerid": 121
    },
    {
      "builderid": 160,
      "buildid": 175393,
      "buildrequestid": 2026744,
      "complete": true,
      "complete_at": 1631977207,
      "masterid": 1,
      "number": 83,
      "properties": {},
      "results": 0,
      "started_at": 1631967810,
      "state_string": "build successful",
      "workerid": 121
    },
    {
      "builderid": 160,
      "buildid": 175456,
      "buildrequestid": 2027216,
      "complete": true,
      "complete_at": 1631995391,
      "masterid": 1,
      "number": 85,
      "properties": {},
      "results": 0,
      "started_at": 1631984996,
      "state_string": "build successful",
      "workerid": 121
    },
    {
      "builderid": 160,
      "buildid": 175556,
      "buildrequestid": 2027632,
      "complete": true,
      "complete_at": 1632003992,
      "masterid": 1,
      "number": 86,
      "properties": {},
      "results": 0,
      "started_at": 1631995390,
      "state_string": "build successful",
      "workerid": 121
    },
    {
      "builderid": 160,
      "buildid": 175572,
      "buildrequestid": 2028264,
      "complete": true,
      "complete_at": 1632010760,
      "masterid": 1,
      "number": 87,
      "properties": {},
      "results": 0,
      "started_at": 1632003991,
      "state_string": "build successful",
      "workerid": 121
    },
    {
      "builderid": 160,
      "buildid": 175614,
      "buildrequestid": 2028403,
      "complete": true,
      "complete_at": 1632037780,
      "masterid": 1,
      "number": 88,
      "properties": {},
      "results": 0,
      "started_at": 1632029222,
      "state_string": "build successful",
      "workerid": 121
    },
    {
      "builderid": 160,
      "buildid": 175641,
      "buildrequestid": 2028546,
      "complete": true,
      "complete_at": 1632045119,
      "masterid": 1,
      "number": 89,
      "properties": {},
      "results": 0,
      "started_at": 1632037780,
      "state_string": "build successful",
      "workerid": 121
    },
    {
      "builderid": 160,
      "buildid": 175700,
      "buildrequestid": 2028807,
      "complete": true,
      "complete_at": 1632063075,
      "masterid": 1,
      "number": 91,
      "properties": {},
      "results": 0,
      "started_at": 1632053211,
      "state_string": "build successful",
      "workerid": 121
    },
    {
      "builderid": 160,
      "buildid": 175668,
      "buildrequestid": 2028671,
      "complete": true,
      "complete_at": 1632053074,
      "masterid": 1,
      "number": 90,
      "properties": {},
      "results": 0,
      "started_at": 1632045119,
      "state_string": "build successful",
      "workerid": 121
    },
    {
      "builderid": 160,
      "buildid": 175792,
      "buildrequestid": 2029686,
      "complete": true,
      "complete_at": 1632072872,
      "masterid": 1,
      "number": 92,
      "properties": {},
      "results": 0,
      "started_at": 1632063074,
      "state_string": "build successful",
      "workerid": 121
    },
    {
      "builderid": 160,
      "buildid": 175847,
      "buildrequestid": 2029999,
      "complete": true,
      "complete_at": 1632078745,
      "masterid": 1,
      "number": 93,
      "properties": {},
      "results": 0,
      "started_at": 1632072872,
      "state_string": "build successful",
      "workerid": 121
    },
    {
      "builderid": 160,
      "buildid": 175880,
      "buildrequestid": 2030384,
      "complete": true,
      "complete_at": 1632091595,
      "masterid": 1,
      "number": 94,
      "properties": {},
      "results": 0,
      "started_at": 1632081840,
      "state_string": "build successful",
      "workerid": 121
    },
    {
      "builderid": 160,
      "buildid": 175975,
      "buildrequestid": 2031254,
      "complete": true,
      "complete_at": 1632100601,
      "masterid": 1,
      "number": 95,
      "properties": {},
      "results": 0,
      "started_at": 1632091595,
      "state_string": "build successful",
      "workerid": 121
    },
    {
      "builderid": 160,
      "buildid": 176037,
      "buildrequestid": 2031687,
      "complete": true,
      "complete_at": 1632109139,
      "masterid": 1,
      "number": 96,
      "properties": {},
      "results": 0,
      "started_at": 1632100600,
      "state_string": "build successful",
      "workerid": 121
    },
    {
      "builderid": 160,
      "buildid": 176065,
      "buildrequestid": 2031803,
      "complete": true,
      "complete_at": 1632118304,
      "masterid": 1,
      "number": 97,
      "properties": {},
      "results": 0,
      "started_at": 1632109138,
      "state_string": "build successful",
      "workerid": 121
    },
    {
      "builderid": 160,
      "buildid": 176119,
      "buildrequestid": 2032177,
      "complete": true,
      "complete_at": 1632126076,
      "masterid": 1,
      "number": 98,
      "properties": {},
      "results": 0,
      "started_at": 1632118304,
      "state_string": "build successful",
      "workerid": 121
    },
    {
      "builderid": 160,
      "buildid": 176164,
      "buildrequestid": 2032420,
      "complete": true,
      "complete_at": 1632135461,
      "masterid": 1,
      "number": 99,
      "properties": {},
      "results": 0,
      "started_at": 1632126076,
      "state_string": "build successful",
      "workerid": 121
    },
    {
      "builderid": 160,
      "buildid": 176239,
      "buildrequestid": 2033302,
      "complete": true,
      "complete_at": 1632148003,
      "masterid": 1,
      "number": 100,
      "properties": {},
      "results": 0,
      "started_at": 1632135461,
      "state_string": "build successful",
      "workerid": 121
    },
    {
      "builderid": 160,
      "buildid": 176356,
      "buildrequestid": 2034495,
      "complete": true,
      "complete_at": 1632160576,
      "masterid": 1,
      "number": 101,
      "properties": {},
      "results": 0,
      "started_at": 1632148003,
      "state_string": "build successful",
      "workerid": 121
    },
    {
      "builderid": 160,
      "buildid": 176515,
      "buildrequestid": 2037631,
      "complete": true,
      "complete_at": 1632170240,
      "masterid": 1,
      "number": 102,
      "properties": {},
      "results": 0,
      "started_at": 1632160575,
      "state_string": "build successful",
      "workerid": 121
    },
    {
      "builderid": 160,
      "buildid": 176604,
      "buildrequestid": 2038448,
      "complete": true,
      "complete_at": 1632181233,
      "masterid": 1,
      "number": 103,
      "properties": {},
      "results": 0,
      "started_at": 1632170240,
      "state_string": "build successful",
      "workerid": 121
    },
    {
      "builderid": 160,
      "buildid": 176696,
      "buildrequestid": 2039736,
      "complete": true,
      "complete_at": 1632191084,
      "masterid": 1,
      "number": 104,
      "properties": {},
      "results": 0,
      "started_at": 1632181233,
      "state_string": "build successful",
      "workerid": 121
    },
    {
      "builderid": 160,
      "buildid": 176758,
      "buildrequestid": 2040385,
      "complete": true,
      "complete_at": 1632202243,
      "masterid": 1,
      "number": 105,
      "properties": {},
      "results": 0,
      "started_at": 1632191083,
      "state_string": "build successful",
      "workerid": 121
    },
    {
      "builderid": 160,
      "buildid": 176834,
      "buildrequestid": 2040396,
      "complete": true,
      "complete_at": 1632212502,
      "masterid": 1,
      "number": 106,
      "properties": {},
      "results": 0,
      "started_at": 1632202243,
      "state_string": "build successful",
      "workerid": 121
    },
    {
      "builderid": 160,
      "buildid": 176893,
      "buildrequestid": 2041537,
      "complete": true,
      "complete_at": 1632223089,
      "masterid": 1,
      "number": 107,
      "properties": {},
      "results": 0,
      "started_at": 1632212502,
      "state_string": "build successful",
      "workerid": 121
    },
    {
      "builderid": 160,
      "buildid": 176993,
      "buildrequestid": 2041748,
      "complete": true,
      "complete_at": 1632232502,
      "masterid": 1,
      "number": 108,
      "properties": {},
      "results": 0,
      "started_at": 1632223088,
      "state_string": "build successful",
      "workerid": 121
    },
    {
      "builderid": 160,
      "buildid": 177090,
      "buildrequestid": 2044049,
      "complete": true,
      "complete_at": 1632242052,
      "masterid": 1,
      "number": 109,
      "properties": {},
      "results": 0,
      "started_at": 1632232502,
      "state_string": "build successful",
      "workerid": 121
    },
    {
      "builderid": 160,
      "buildid": 177202,
      "buildrequestid": 2046721,
      "complete": true,
      "complete_at": 1632256151,
      "masterid": 1,
      "number": 110,
      "properties": {},
      "results": 0,
      "started_at": 1632242052,
      "state_string": "build successful",
      "workerid": 121
    },
    {
      "builderid": 160,
      "buildid": 177374,
      "buildrequestid": 2049271,
      "complete": true,
      "complete_at": 1632264176,
      "masterid": 1,
      "number": 111,
      "properties": {},
      "results": 0,
      "started_at": 1632256151,
      "state_string": "build successful",
      "workerid": 121
    },
    {
      "builderid": 160,
      "buildid": 177462,
      "buildrequestid": 2050603,
      "complete": true,
      "complete_at": 1632273997,
      "masterid": 1,
      "number": 112,
      "properties": {},
      "results": 0,
      "started_at": 1632264176,
      "state_string": "build successful",
      "workerid": 121
    },
    {
      "builderid": 160,
      "buildid": 177506,
      "buildrequestid": 2050987,
      "complete": true,
      "complete_at": 1632283204,
      "masterid": 1,
      "number": 113,
      "properties": {},
      "results": 0,
      "started_at": 1632273996,
      "state_string": "build successful",
      "workerid": 121
    },
    {
      "builderid": 160,
      "buildid": 177606,
      "buildrequestid": 2052325,
      "complete": true,
      "complete_at": 1632294651,
      "masterid": 1,
      "number": 114,
      "properties": {},
      "results": 0,
      "started_at": 1632283204,
      "state_string": "build successful",
      "workerid": 121
    },
    {
      "builderid": 160,
      "buildid": 177654,
      "buildrequestid": 2052823,
      "complete": true,
      "complete_at": 1632306059,
      "masterid": 1,
      "number": 115,
      "properties": {},
      "results": 0,
      "started_at": 1632294651,
      "state_string": "build successful",
      "workerid": 121
    },
    {
      "builderid": 160,
      "buildid": 177785,
      "buildrequestid": 2054814,
      "complete": true,
      "complete_at": 1632323170,
      "masterid": 1,
      "number": 116,
      "properties": {},
      "results": 0,
      "started_at": 1632306058,
      "state_string": "build successful",
      "workerid": 121
    },
    {
      "builderid": 160,
      "buildid": 177985,
      "buildrequestid": 2056842,
      "complete": true,
      "complete_at": 1632335620,
      "masterid": 1,
      "number": 117,
      "properties": {},
      "results": 0,
      "started_at": 1632323170,
      "state_string": "build successful",
      "workerid": 121
    },
    {
      "builderid": 160,
      "buildid": 178142,
      "buildrequestid": 2057162,
      "complete": true,
      "complete_at": 1632348071,
      "masterid": 1,
      "number": 118,
      "properties": {},
      "results": 0,
      "started_at": 1632335620,
      "state_string": "build successful",
      "workerid": 121
    },
    {
      "builderid": 160,
      "buildid": 178261,
      "buildrequestid": 2061377,
      "complete": true,
      "complete_at": 1632357245,
      "masterid": 1,
      "number": 119,
      "properties": {},
      "results": 0,
      "started_at": 1632348070,
      "state_string": "build successful",
      "workerid": 121
    },
    {
      "builderid": 160,
      "buildid": 178299,
      "buildrequestid": 2061563,
      "complete": true,
      "complete_at": 1632367260,
      "masterid": 1,
      "number": 120,
      "properties": {},
      "results": 0,
      "started_at": 1632357244,
      "state_string": "build successful",
      "workerid": 121
    },
    {
      "builderid": 160,
      "buildid": 178459,
      "buildrequestid": 2063565,
      "complete": true,
      "complete_at": 1632386191,
      "masterid": 1,
      "number": 122,
      "properties": {},
      "results": 5,
      "started_at": 1632377467,
      "state_string": "retry lost connection build (retry)",
      "workerid": 121
    },
    {
      "builderid": 160,
      "buildid": 178395,
      "buildrequestid": 2062731,
      "complete": true,
      "complete_at": 1632377467,
      "masterid": 1,
      "number": 121,
      "properties": {},
      "results": 0,
      "started_at": 1632367260,
      "state_string": "build successful",
      "workerid": 121
    }
  ],
  "meta": {
    "total": 122
  }
}