{
  "builds": [
    {
      "builderid": 187,
      "buildid": 182750,
      "buildrequestid": 2142588,
      "complete": true,
      "complete_at": 1633112403,
      "masterid": 2,
      "number": 99,
      "properties": {},
      "results": 2,
      "started_at": 1633112389,
      "state_string": "failed 'cmake ../llvm.src/llvm ...'",
      "workerid": 147
    },
    {
      "builderid": 187,
      "buildid": 182685,
      "buildrequestid": 2141130,
      "complete": true,
      "complete_at": 1633106263,
      "masterid": 2,
      "number": 91,
      "properties": {},
      "results": 2,
      "started_at": 1633106246,
      "state_string": "failed 'cmake ../llvm.src/llvm ...'",
      "workerid": 147
    },
    {
      "builderid": 187,
      "buildid": 183256,
      "buildrequestid": 2150393,
      "complete": true,
      "complete_at": 1633238081,
      "masterid": 2,
      "number": 134,
      "properties": {},
      "results": 2,
      "started_at": 1633237578,
      "state_string": "failed 1018 expected passes 40 unsupported tests 41 unexpected failures (failure)",
      "workerid": 147
    },
    {
      "builderid": 187,
      "buildid": 183257,
      "buildrequestid": 2150419,
      "complete": true,
      "complete_at": 1633238252,
      "masterid": 2,
      "number": 135,
      "properties": {},
      "results": 0,
      "started_at": 1633238081,
      "state_string": "build successful",
      "workerid": 147
    },
    {
      "builderid": 187,
      "buildid": 182725,
      "buildrequestid": 2142336,
      "complete": true,
      "complete_at": 1633109115,
      "masterid": 2,
      "number": 96,
      "properties": {},
      "results": 2,
      "started_at": 1633109099,
      "state_string": "failed 'cmake ../llvm.src/llvm ...'",
      "workerid": 147
    },
    {
      "builderid": 187,
      "buildid": 182860,
      "buildrequestid": 2144423,
      "complete": true,
      "complete_at": 1633122041,
      "masterid": 2,
      "number": 109,
      "properties": {},
      "results": 2,
      "started_at": 1633122024,
      "state_string": "failed 'cmake ../llvm.src/llvm ...'",
      "workerid": 147
    },
    {
      "builderid": 187,
      "buildid": 182853,
      "buildrequestid": 2144267,
      "complete": true,
      "complete_at": 1633121436,
      "masterid": 2,
      "number": 108,
      "properties": {},
      "results": 2,
      "started_at": 1633121420,
      "state_string": "failed 'cmake ../llvm.src/llvm ...'",
      "workerid": 147
    },
    {
      "builderid": 187,
      "buildid": 182874,
      "buildrequestid": 2144577,
      "complete": true,
      "complete_at": 1633123239,
      "masterid": 2,
      "number": 111,
      "properties": {},
      "results": 2,
      "started_at": 1633123223,
      "state_string": "failed 'cmake ../llvm.src/llvm ...'",
      "workerid": 147
    },
    {
      "builderid": 187,
      "buildid": 182875,
      "buildrequestid": 2144598,
      "complete": true,
      "complete_at": 1633123360,
      "masterid": 2,
      "number": 112,
      "properties": {},
      "results": 2,
      "started_at": 1633123344,
      "state_string": "failed 'cmake ../llvm.src/llvm ...'",
      "workerid": 147
    },
    {
      "builderid": 187,
      "buildid": 182870,
      "buildrequestid": 2144550,
      "complete": true,
      "complete_at": 1633123114,
      "masterid": 2,
      "number": 110,
      "properties": {},
      "results": 2,
      "started_at": 1633123099,
      "state_string": "failed 'cmake ../llvm.src/llvm ...'",
      "workerid": 147
    },
    {
      "builderid": 187,
      "buildid": 182882,
      "buildrequestid": 2144818,
      "complete": true,
      "complete_at": 1633124072,
      "masterid": 2,
      "number": 113,
      "properties": {},
      "results": 2,
      "started_at": 1633124056,
      "state_string": "failed 'cmake ../llvm.src/llvm ...'",
      "workerid": 147
    },
    {
      "builderid": 187,
      "buildid": 182947,
      "buildrequestid": 2145912,
      "complete": true,
      "complete_at": 1633131309,
      "masterid": 2,
      "number": 116,
      "properties": {},
      "results": 2,
      "started_at": 1633131293,
      "state_string": "failed 'cmake ../llvm.src/llvm ...'",
      "workerid": 147
    },
    {
      "builderid": 187,
      "buildid": 181796,
      "buildrequestid": 2126221,
      "complete": true,
      "complete_at": 1632964971,
      "masterid": 2,
      "number": 1,
      "properties": {},
      "results": 2,
      "started_at": 1632964757,
      "state_string": "failed 'cmake ../llvm.src/llvm ...'",
      "workerid": 147
    },
    {
      "builderid": 187,
      "buildid": 181799,
      "buildrequestid": 2126878,
      "complete": true,
      "complete_at": 1632964974,
      "masterid": 2,
      "number": 2,
      "properties": {},
      "results": 2,
      "started_at": 1632964970,
      "state_string": "failed 'cmake ../llvm.src/llvm ...'",
      "workerid": 147
    },
    {
      "builderid": 187,
      "buildid": 181941,
      "buildrequestid": 2127683,
      "complete": true,
      "complete_at": 1632981511,
      "masterid": 2,
      "number": 15,
      "properties": {},
      "results": 2,
      "started_at": 1632981497,
      "state_string": "failed 'cmake ../llvm.src/llvm ...'",
      "workerid": 147
    },
    {
      "builderid": 187,
      "buildid": 181800,
      "buildrequestid": 2126894,
      "complete": true,
      "complete_at": 1632964976,
      "masterid": 2,
      "number": 3,
      "properties": {},
      "results": 2,
      "started_at": 1632964973,
      "state_string": "failed 'cmake ../llvm.src/llvm ...'",
      "workerid": 147
    },
    {
      "builderid": 187,
      "buildid": 181919,
      "buildrequestid": 2127472,
      "complete": true,
      "complete_at": 1632978562,
      "masterid": 2,
      "number": 12,
      "properties": {},
      "results": 2,
      "started_at": 1632978550,
      "state_string": "failed 'cmake ../llvm.src/llvm ...'",
      "workerid": 147
    },
    {
      "builderid": 187,
      "buildid": 181971,
      "buildrequestid": 2128104,
      "complete": true,
      "complete_at": 1632984511,
      "masterid": 2,
      "number": 18,
      "properties": {},
      "results": 2,
      "started_at": 1632984497,
      "state_string": "failed 'cmake ../llvm.src/llvm ...'",
      "workerid": 147
    },
    {
      "builderid": 187,
      "buildid": 181947,
      "buildrequestid": 2127798,
      "complete": true,
      "complete_at": 1632981748,
      "masterid": 2,
      "number": 16,
      "properties": {},
      "results": 2,
      "started_at": 1632981735,
      "state_string": "failed 'cmake ../llvm.src/llvm ...'",
      "workerid": 147
    },
    {
      "builderid": 187,
      "buildid": 181977,
      "buildrequestid": 2128241,
      "complete": true,
      "complete_at": 1632987565,
      "masterid": 2,
      "number": 19,
      "properties": {},
      "results": 2,
      "started_at": 1632987553,
      "state_string": "failed 'cmake ../llvm.src/llvm ...'",
      "workerid": 147
    },
    {
      "builderid": 187,
      "buildid": 181909,
      "buildrequestid": 2127427,
      "complete": true,
      "complete_at": 1632977127,
      "masterid": 2,
      "number": 9,
      "properties": {},
      "results": 2,
      "started_at": 1632977115,
      "state_string": "failed 'cmake ../llvm.src/llvm ...'",
      "workerid": 147
    },
    {
      "builderid": 187,
      "buildid": 181997,
      "buildrequestid": 2128557,
      "complete": true,
      "complete_at": 1632989920,
      "masterid": 2,
      "number": 21,
      "properties": {},
      "results": 2,
      "started_at": 1632989896,
      "state_string": "failed 'cmake ../llvm.src/llvm ...'",
      "workerid": 147
    },
    {
      "builderid": 187,
      "buildid": 181953,
      "buildrequestid": 2128031,
      "complete": true,
      "complete_at": 1632982105,
      "masterid": 2,
      "number": 17,
      "properties": {},
      "results": 2,
      "started_at": 1632982091,
      "state_string": "failed 'cmake ../llvm.src/llvm ...'",
      "workerid": 147
    },
    {
      "builderid": 187,
      "buildid": 181817,
      "buildrequestid": 2126927,
      "complete": true,
      "complete_at": 1632966717,
      "masterid": 2,
      "number": 4,
      "properties": {},
      "results": 2,
      "started_at": 1632966713,
      "state_string": "failed 'cmake ../llvm.src/llvm ...'",
      "workerid": 147
    },
    {
      "builderid": 187,
      "buildid": 181915,
      "buildrequestid": 2127445,
      "complete": true,
      "complete_at": 1632978207,
      "masterid": 2,
      "number": 10,
      "properties": {},
      "results": 2,
      "started_at": 1632978195,
      "state_string": "failed 'cmake ../llvm.src/llvm ...'",
      "workerid": 147
    },
    {
      "builderid": 187,
      "buildid": 181841,
      "buildrequestid": 2127172,
      "complete": true,
      "complete_at": 1632968542,
      "masterid": 2,
      "number": 5,
      "properties": {},
      "results": 2,
      "started_at": 1632968537,
      "state_string": "failed 'cmake ../llvm.src/llvm ...'",
      "workerid": 147
    },
    {
      "builderid": 187,
      "buildid": 181922,
      "buildrequestid": 2127499,
      "complete": true,
      "complete_at": 1632978687,
      "masterid": 2,
      "number": 13,
      "properties": {},
      "results": 2,
      "started_at": 1632978675,
      "state_string": "failed 'cmake ../llvm.src/llvm ...'",
      "workerid": 147
    },
    {
      "builderid": 187,
      "buildid": 181926,
      "buildrequestid": 2127524,
      "complete": true,
      "complete_at": 1632979530,
      "masterid": 2,
      "number": 14,
      "properties": {},
      "results": 2,
      "started_at": 1632979517,
      "state_string": "failed 'cmake ../llvm.src/llvm ...'",
      "workerid": 147
    },
    {
      "builderid": 187,
      "buildid": 181979,
      "buildrequestid": 2128261,
      "complete": true,
      "complete_at": 1632987578,
      "masterid": 2,
      "number": 20,
      "properties": {},
      "results": 2,
      "started_at": 1632987566,
      "state_string": "failed 'cmake ../llvm.src/llvm ...'",
      "workerid": 147
    },
    {
      "builderid": 187,
      "buildid": 182840,
      "buildrequestid": 2144236,
      "complete": true,
      "complete_at": 1633119703,
      "masterid": 2,
      "number": 107,
      "properties": {},
      "results": 2,
      "started_at": 1633119687,
      "state_string": "'cmake ../llvm.src/llvm ...'",
      "workerid": 147
    },
    {
      "builderid": 187,
      "buildid": 182957,
      "buildrequestid": 2146034,
      "complete": true,
      "complete_at": 1633132145,
      "masterid": 2,
      "number": 117,
      "properties": {},
      "results": 5,
      "started_at": 1633132133,
      "state_string": "retry lost connection 'cmake ../llvm.src/llvm ...'",
      "workerid": 147
    },
    {
      "builderid": 187,
      "buildid": 182993,
      "buildrequestid": 2146432,
      "complete": true,
      "complete_at": 1633148675,
      "masterid": 2,
      "number": 122,
      "properties": {},
      "results": 2,
      "started_at": 1633148418,
      "state_string": "failed 933 expected passes 129 unexpected failures 37 unsupported tests (failure)",
      "workerid": 147
    },
    {
      "builderid": 187,
      "buildid": 181916,
      "buildrequestid": 2127466,
      "complete": true,
      "complete_at": 1632978243,
      "masterid": 2,
      "number": 11,
      "properties": {},
      "results": 2,
      "started_at": 1632978231,
      "state_string": "failed 'cmake ../llvm.src/llvm ...'",
      "workerid": 147
    },
    {
      "builderid": 187,
      "buildid": 182990,
      "buildrequestid": 2146425,
      "complete": true,
      "complete_at": 1633145854,
      "masterid": 2,
      "number": 120,
      "properties": {},
      "results": 2,
      "started_at": 1633145624,
      "state_string": "failed 'cmake ../llvm.src/llvm ...'",
      "workerid": 147
    },
    {
      "builderid": 187,
      "buildid": 182996,
      "buildrequestid": 2146459,
      "complete": true,
      "complete_at": 1633150129,
      "masterid": 2,
      "number": 123,
      "properties": {},
      "results": 2,
      "started_at": 1633149978,
      "state_string": "failed 934 expected passes 128 unexpected failures 37 unsupported tests (failure)",
      "workerid": 147
    },
    {
      "builderid": 187,
      "buildid": 182008,
      "buildrequestid": 2128716,
      "complete": true,
      "complete_at": 1632990630,
      "masterid": 2,
      "number": 22,
      "properties": {},
      "results": 2,
      "started_at": 1632990616,
      "state_string": "failed 'cmake ../llvm.src/llvm ...'",
      "workerid": 147
    },
    {
      "builderid": 187,
      "buildid": 182011,
      "buildrequestid": 2128831,
      "complete": true,
      "complete_at": 1632990834,
      "masterid": 2,
      "number": 23,
      "properties": {},
      "results": 2,
      "started_at": 1632990822,
      "state_string": "failed 'cmake ../llvm.src/llvm ...'",
      "workerid": 147
    },
    {
      "builderid": 187,
      "buildid": 182085,
      "buildrequestid": 2129795,
      "complete": true,
      "complete_at": 1633009433,
      "masterid": 2,
      "number": 28,
      "properties": {},
      "results": 2,
      "started_at": 1633009421,
      "state_string": "failed 'cmake ../llvm.src/llvm ...'",
      "workerid": 147
    },
    {
      "builderid": 187,
      "buildid": 182049,
      "buildrequestid": 2129363,
      "complete": true,
      "complete_at": 1633000675,
      "masterid": 2,
      "number": 24,
      "properties": {},
      "results": 2,
      "started_at": 1633000662,
      "state_string": "failed 'cmake ../llvm.src/llvm ...'",
      "workerid": 147
    },
    {
      "builderid": 187,
      "buildid": 182089,
      "buildrequestid": 2129920,
      "complete": true,
      "complete_at": 1633010121,
      "masterid": 2,
      "number": 29,
      "properties": {},
      "results": 2,
      "started_at": 1633010109,
      "state_string": "failed 'cmake ../llvm.src/llvm ...'",
      "workerid": 147
    },
    {
      "builderid": 187,
      "buildid": 182062,
      "buildrequestid": 2129572,
      "complete": true,
      "complete_at": 1633002802,
      "masterid": 2,
      "number": 26,
      "properties": {},
      "results": 2,
      "started_at": 1633002790,
      "state_string": "failed 'cmake ../llvm.src/llvm ...'",
      "workerid": 147
    },
    {
      "builderid": 187,
      "buildid": 182074,
      "buildrequestid": 2129693,
      "complete": true,
      "complete_at": 1633008828,
      "masterid": 2,
      "number": 27,
      "properties": {},
      "results": 2,
      "started_at": 1633008816,
      "state_string": "failed 'cmake ../llvm.src/llvm ...'",
      "workerid": 147
    },
    {
      "builderid": 187,
      "buildid": 182059,
      "buildrequestid": 2129433,
      "complete": true,
      "complete_at": 1633001565,
      "masterid": 2,
      "number": 25,
      "properties": {},
      "results": 2,
      "started_at": 1633001551,
      "state_string": "failed 'cmake ../llvm.src/llvm ...'",
      "workerid": 147
    },
    {
      "builderid": 187,
      "buildid": 182991,
      "buildrequestid": 2146426,
      "complete": true,
      "complete_at": 1633147660,
      "masterid": 2,
      "number": 121,
      "properties": {},
      "results": 2,
      "started_at": 1633147041,
      "state_string": "failed 933 expected passes 129 unexpected failures 37 unsupported tests (failure)",
      "workerid": 147
    },
    {
      "builderid": 187,
      "buildid": 183262,
      "buildrequestid": 2150445,
      "complete": true,
      "complete_at": 1633239854,
      "masterid": 2,
      "number": 136,
      "properties": {},
      "results": 0,
      "started_at": 1633239503,
      "state_string": "build successful",
      "workerid": 147
    },
    {
      "builderid": 187,
      "buildid": 182095,
      "buildrequestid": 2130051,
      "complete": true,
      "complete_at": 1633012194,
      "masterid": 2,
      "number": 30,
      "properties": {},
      "results": 2,
      "started_at": 1633012181,
      "state_string": "failed 'cmake ../llvm.src/llvm ...'",
      "workerid": 147
    },
    {
      "builderid": 187,
      "buildid": 183283,
      "buildrequestid": 2150664,
      "complete": true,
      "complete_at": 1633251679,
      "masterid": 2,
      "number": 138,
      "properties": {},
      "results": 0,
      "started_at": 1633251542,
      "state_string": "build successful",
      "workerid": 147
    },
    {
      "builderid": 187,
      "buildid": 182096,
      "buildrequestid": 2130125,
      "complete": true,
      "complete_at": 1633012300,
      "masterid": 2,
      "number": 31,
      "properties": {},
      "results": 2,
      "started_at": 1633012288,
      "state_string": "failed 'cmake ../llvm.src/llvm ...'",
      "workerid": 147
    },
    {
      "builderid": 187,
      "buildid": 182165,
      "buildrequestid": 2131474,
      "complete": true,
      "complete_at": 1633019598,
      "masterid": 2,
      "number": 39,
      "properties": {},
      "results": 2,
      "started_at": 1633019587,
      "state_string": "failed 'cmake ../llvm.src/llvm ...'",
      "workerid": 147
    },
    {
      "builderid": 187,
      "buildid": 182098,
      "buildrequestid": 2130401,
      "complete": true,
      "complete_at": 1633012459,
      "masterid": 2,
      "number": 32,
      "properties": {},
      "results": 2,
      "started_at": 1633012447,
      "state_string": "failed 'cmake ../llvm.src/llvm ...'",
      "workerid": 147
    },
    {
      "builderid": 187,
      "buildid": 182184,
      "buildrequestid": 2131908,
      "complete": true,
      "complete_at": 1633021111,
      "masterid": 2,
      "number": 42,
      "properties": {},
      "results": 2,
      "started_at": 1633021098,
      "state_string": "failed 'cmake ../llvm.src/llvm ...'",
      "workerid": 147
    },
    {
      "builderid": 187,
      "buildid": 182132,
      "buildrequestid": 2131059,
      "complete": true,
      "complete_at": 1633014993,
      "masterid": 2,
      "number": 36,
      "properties": {},
      "results": 2,
      "started_at": 1633014980,
      "state_string": "'cmake ../llvm.src/llvm ...'",
      "workerid": 147
    },
    {
      "builderid": 187,
      "buildid": 182120,
      "buildrequestid": 2130766,
      "complete": true,
      "complete_at": 1633014390,
      "masterid": 2,
      "number": 34,
      "properties": {},
      "results": 2,
      "started_at": 1633014377,
      "state_string": "'cmake ../llvm.src/llvm ...'",
      "workerid": 147
    },
    {
      "builderid": 187,
      "buildid": 182171,
      "buildrequestid": 2131549,
      "complete": true,
      "complete_at": 1633020512,
      "masterid": 2,
      "number": 40,
      "properties": {},
      "results": 2,
      "started_at": 1633020499,
      "state_string": "failed 'cmake ../llvm.src/llvm ...'",
      "workerid": 147
    },
    {
      "builderid": 187,
      "buildid": 182105,
      "buildrequestid": 2130544,
      "complete": true,
      "complete_at": 1633012955,
      "masterid": 2,
      "number": 33,
      "properties": {},
      "results": 2,
      "started_at": 1633012942,
      "state_string": "failed 'cmake ../llvm.src/llvm ...'",
      "workerid": 147
    },
    {
      "builderid": 187,
      "buildid": 182162,
      "buildrequestid": 2131364,
      "complete": true,
      "complete_at": 1633019552,
      "masterid": 2,
      "number": 38,
      "properties": {},
      "results": 2,
      "started_at": 1633019537,
      "state_string": "failed 'cmake ../llvm.src/llvm ...'",
      "workerid": 147
    },
    {
      "builderid": 187,
      "buildid": 182212,
      "buildrequestid": 2132157,
      "complete": true,
      "complete_at": 1633024523,
      "masterid": 2,
      "number": 44,
      "properties": {},
      "results": 2,
      "started_at": 1633024510,
      "state_string": "failed 'cmake ../llvm.src/llvm ...'",
      "workerid": 147
    },
    {
      "builderid": 187,
      "buildid": 182231,
      "buildrequestid": 2132707,
      "complete": true,
      "complete_at": 1633027402,
      "masterid": 2,
      "number": 45,
      "properties": {},
      "results": 2,
      "started_at": 1633027390,
      "state_string": "failed 'cmake ../llvm.src/llvm ...'",
      "workerid": 147
    },
    {
      "builderid": 187,
      "buildid": 182177,
      "buildrequestid": 2131762,
      "complete": true,
      "complete_at": 1633020625,
      "masterid": 2,
      "number": 41,
      "properties": {},
      "results": 2,
      "started_at": 1633020612,
      "state_string": "failed 'cmake ../llvm.src/llvm ...'",
      "workerid": 147
    },
    {
      "builderid": 187,
      "buildid": 182128,
      "buildrequestid": 2130958,
      "complete": true,
      "complete_at": 1633014817,
      "masterid": 2,
      "number": 35,
      "properties": {},
      "results": 2,
      "started_at": 1633014805,
      "state_string": "failed 'cmake ../llvm.src/llvm ...'",
      "workerid": 147
    },
    {
      "builderid": 187,
      "buildid": 182149,
      "buildrequestid": 2131228,
      "complete": true,
      "complete_at": 1633017270,
      "masterid": 2,
      "number": 37,
      "properties": {},
      "results": 2,
      "started_at": 1633017258,
      "state_string": "failed 'cmake ../llvm.src/llvm ...'",
      "workerid": 147
    },
    {
      "builderid": 187,
      "buildid": 182204,
      "buildrequestid": 2132054,
      "complete": true,
      "complete_at": 1633023380,
      "masterid": 2,
      "number": 43,
      "properties": {},
      "results": 2,
      "started_at": 1633023367,
      "state_string": "failed 'cmake ../llvm.src/llvm ...'",
      "workerid": 147
    },
    {
      "builderid": 187,
      "buildid": 182303,
      "buildrequestid": 2134101,
      "complete": true,
      "complete_at": 1633033399,
      "masterid": 2,
      "number": 54,
      "properties": {},
      "results": 2,
      "started_at": 1633033387,
      "state_string": "failed 'cmake ../llvm.src/llvm ...'",
      "workerid": 147
    },
    {
      "builderid": 187,
      "buildid": 182273,
      "buildrequestid": 2133545,
      "complete": true,
      "complete_at": 1633030596,
      "masterid": 2,
      "number": 51,
      "properties": {},
      "results": 2,
      "started_at": 1633030584,
      "state_string": "failed 'cmake ../llvm.src/llvm ...'",
      "workerid": 147
    },
    {
      "builderid": 187,
      "buildid": 182236,
      "buildrequestid": 2132725,
      "complete": true,
      "complete_at": 1633027682,
      "masterid": 2,
      "number": 46,
      "properties": {},
      "results": 2,
      "started_at": 1633027670,
      "state_string": "failed 'cmake ../llvm.src/llvm ...'",
      "workerid": 147
    },
    {
      "builderid": 187,
      "buildid": 182308,
      "buildrequestid": 2134111,
      "complete": true,
      "complete_at": 1633033802,
      "masterid": 2,
      "number": 55,
      "properties": {},
      "results": 2,
      "started_at": 1633033790,
      "state_string": "failed 'cmake ../llvm.src/llvm ...'",
      "workerid": 147
    },
    {
      "builderid": 187,
      "buildid": 182250,
      "buildrequestid": 2133131,
      "complete": true,
      "complete_at": 1633028915,
      "masterid": 2,
      "number": 48,
      "properties": {},
      "results": 2,
      "started_at": 1633028902,
      "state_string": "failed 'cmake ../llvm.src/llvm ...'",
      "workerid": 147
    },
    {
      "builderid": 187,
      "buildid": 182246,
      "buildrequestid": 2132857,
      "complete": true,
      "complete_at": 1633028755,
      "masterid": 2,
      "number": 47,
      "properties": {},
      "results": 2,
      "started_at": 1633028743,
      "state_string": "failed 'cmake ../llvm.src/llvm ...'",
      "workerid": 147
    },
    {
      "builderid": 187,
      "buildid": 182256,
      "buildrequestid": 2133281,
      "complete": true,
      "complete_at": 1633029509,
      "masterid": 2,
      "number": 49,
      "properties": {},
      "results": 2,
      "started_at": 1633029497,
      "state_string": "failed 'cmake ../llvm.src/llvm ...'",
      "workerid": 147
    },
    {
      "builderid": 187,
      "buildid": 182327,
      "buildrequestid": 2134448,
      "complete": true,
      "complete_at": 1633035748,
      "masterid": 2,
      "number": 57,
      "properties": {},
      "results": 2,
      "started_at": 1633035734,
      "state_string": "failed 'cmake ../llvm.src/llvm ...'",
      "workerid": 147
    },
    {
      "builderid": 187,
      "buildid": 182268,
      "buildrequestid": 2133400,
      "complete": true,
      "complete_at": 1633030471,
      "masterid": 2,
      "number": 50,
      "properties": {},
      "results": 2,
      "started_at": 1633030459,
      "state_string": "failed 'cmake ../llvm.src/llvm ...'",
      "workerid": 147
    },
    {
      "builderid": 187,
      "buildid": 182339,
      "buildrequestid": 2134691,
      "complete": true,
      "complete_at": 1633037203,
      "masterid": 2,
      "number": 58,
      "properties": {},
      "results": 2,
      "started_at": 1633037190,
      "state_string": "failed 'cmake ../llvm.src/llvm ...'",
      "workerid": 147
    },
    {
      "builderid": 187,
      "buildid": 182280,
      "buildrequestid": 2133715,
      "complete": true,
      "complete_at": 1633030964,
      "masterid": 2,
      "number": 52,
      "properties": {},
      "results": 2,
      "started_at": 1633030952,
      "state_string": "failed 'cmake ../llvm.src/llvm ...'",
      "workerid": 147
    },
    {
      "builderid": 187,
      "buildid": 182318,
      "buildrequestid": 2134259,
      "complete": true,
      "complete_at": 1633034277,
      "masterid": 2,
      "number": 56,
      "properties": {},
      "results": 2,
      "started_at": 1633034265,
      "state_string": "failed 'cmake ../llvm.src/llvm ...'",
      "workerid": 147
    },
    {
      "builderid": 187,
      "buildid": 182346,
      "buildrequestid": 2134795,
      "complete": true,
      "complete_at": 1633037637,
      "masterid": 2,
      "number": 59,
      "properties": {},
      "results": 2,
      "started_at": 1633037625,
      "state_string": "failed 'cmake ../llvm.src/llvm ...'",
      "workerid": 147
    },
    {
      "builderid": 187,
      "buildid": 182288,
      "buildrequestid": 2133899,
      "complete": true,
      "complete_at": 1633031788,
      "masterid": 2,
      "number": 53,
      "properties": {},
      "results": 2,
      "started_at": 1633031775,
      "state_string": "failed 'cmake ../llvm.src/llvm ...'",
      "workerid": 147
    },
    {
      "builderid": 187,
      "buildid": 183197,
      "buildrequestid": 2149696,
      "complete": true,
      "complete_at": 1633221820,
      "masterid": 2,
      "number": 125,
      "properties": {},
      "results": 2,
      "started_at": 1633221489,
      "state_string": "failed 985 expected passes 40 unsupported tests 74 unexpected failures (failure)",
      "workerid": 147
    },
    {
      "builderid": 187,
      "buildid": 183195,
      "buildrequestid": 2149677,
      "complete": true,
      "complete_at": 1633219225,
      "masterid": 2,
      "number": 124,
      "properties": {},
      "results": 2,
      "started_at": 1633218986,
      "state_string": "failed 'cmake ../llvm.src/llvm ...'",
      "workerid": 147
    },
    {
      "builderid": 187,
      "buildid": 183206,
      "buildrequestid": 2149775,
      "complete": true,
      "complete_at": 1633226086,
      "masterid": 2,
      "number": 127,
      "properties": {},
      "results": 2,
      "started_at": 1633225949,
      "state_string": "failed 985 expected passes 40 unsupported tests 74 unexpected failures (failure)",
      "workerid": 147
    },
    {
      "builderid": 187,
      "buildid": 183264,
      "buildrequestid": 2150460,
      "complete": true,
      "complete_at": 1633246239,
      "masterid": 2,
      "number": 137,
      "properties": {},
      "results": 0,
      "started_at": 1633246099,
      "state_string": "build successful",
      "workerid": 147
    },
    {
      "builderid": 187,
      "buildid": 182395,
      "buildrequestid": 2135387,
      "complete": true,
      "complete_at": 1633046156,
      "masterid": 2,
      "number": 64,
      "properties": {},
      "results": 2,
      "started_at": 1633046144,
      "state_string": "failed 'cmake ../llvm.src/llvm ...'",
      "workerid": 147
    },
    {
      "builderid": 187,
      "buildid": 182383,
      "buildrequestid": 2135262,
      "complete": true,
      "complete_at": 1633043910,
      "masterid": 2,
      "number": 63,
      "properties": {},
      "results": 2,
      "started_at": 1633043896,
      "state_string": "failed 'cmake ../llvm.src/llvm ...'",
      "workerid": 147
    },
    {
      "builderid": 187,
      "buildid": 182408,
      "buildrequestid": 2135742,
      "complete": true,
      "complete_at": 1633049445,
      "masterid": 2,
      "number": 66,
      "properties": {},
      "results": 2,
      "started_at": 1633049433,
      "state_string": "failed 'cmake ../llvm.src/llvm ...'",
      "workerid": 147
    },
    {
      "builderid": 187,
      "buildid": 182436,
      "buildrequestid": 2136134,
      "complete": true,
      "complete_at": 1633060893,
      "masterid": 2,
      "number": 69,
      "properties": {},
      "results": 2,
      "started_at": 1633060876,
      "state_string": "failed 'cmake ../llvm.src/llvm ...'",
      "workerid": 147
    },
    {
      "builderid": 187,
      "buildid": 182423,
      "buildrequestid": 2136003,
      "complete": true,
      "complete_at": 1633057915,
      "masterid": 2,
      "number": 68,
      "properties": {},
      "results": 2,
      "started_at": 1633057899,
      "state_string": "failed 'cmake ../llvm.src/llvm ...'",
      "workerid": 147
    },
    {
      "builderid": 187,
      "buildid": 182355,
      "buildrequestid": 2134919,
      "complete": true,
      "complete_at": 1633038237,
      "masterid": 2,
      "number": 60,
      "properties": {},
      "results": 2,
      "started_at": 1633038224,
      "state_string": "failed 'cmake ../llvm.src/llvm ...'",
      "workerid": 147
    },
    {
      "builderid": 187,
      "buildid": 182940,
      "buildrequestid": 2145744,
      "complete": true,
      "complete_at": 1633131115,
      "masterid": 2,
      "number": 114,
      "properties": {},
      "results": 2,
      "started_at": 1633130884,
      "state_string": "failed 'cmake ../llvm.src/llvm ...'",
      "workerid": 147
    },
    {
      "builderid": 187,
      "buildid": 182406,
      "buildrequestid": 2135623,
      "complete": true,
      "complete_at": 1633049191,
      "masterid": 2,
      "number": 65,
      "properties": {},
      "results": 2,
      "started_at": 1633049177,
      "state_string": "failed 'cmake ../llvm.src/llvm ...'",
      "workerid": 147
    },
    {
      "builderid": 187,
      "buildid": 182367,
      "buildrequestid": 2135090,
      "complete": true,
      "complete_at": 1633040159,
      "masterid": 2,
      "number": 61,
      "properties": {},
      "results": 2,
      "started_at": 1633040147,
      "state_string": "'cmake ../llvm.src/llvm ...'",
      "workerid": 147
    },
    {
      "builderid": 187,
      "buildid": 182420,
      "buildrequestid": 2135852,
      "complete": true,
      "complete_at": 1633055199,
      "masterid": 2,
      "number": 67,
      "properties": {},
      "results": 2,
      "started_at": 1633055183,
      "state_string": "failed 'cmake ../llvm.src/llvm ...'",
      "workerid": 147
    },
    {
      "builderid": 187,
      "buildid": 183199,
      "buildrequestid": 2149697,
      "complete": true,
      "complete_at": 1633222673,
      "masterid": 2,
      "number": 126,
      "properties": {},
      "results": 2,
      "started_at": 1633222539,
      "state_string": "failed 985 expected passes 40 unsupported tests 74 unexpected failures (failure)",
      "workerid": 147
    },
    {
      "builderid": 187,
      "buildid": 183231,
      "buildrequestid": 2150012,
      "complete": true,
      "complete_at": 1633232313,
      "masterid": 2,
      "number": 130,
      "properties": {},
      "results": 2,
      "started_at": 1633232177,
      "state_string": "failed 1011 expected passes 40 unsupported tests 48 unexpected failures (failure)",
      "workerid": 147
    },
    {
      "builderid": 187,
      "buildid": 183230,
      "buildrequestid": 2149999,
      "complete": true,
      "complete_at": 1633231956,
      "masterid": 2,
      "number": 129,
      "properties": {},
      "results": 2,
      "started_at": 1633231818,
      "state_string": "failed 994 expected passes 40 unsupported tests 65 unexpected failures (failure)",
      "workerid": 147
    },
    {
      "builderid": 187,
      "buildid": 183233,
      "buildrequestid": 2150045,
      "complete": true,
      "complete_at": 1633232794,
      "masterid": 2,
      "number": 131,
      "properties": {},
      "results": 2,
      "started_at": 1633232659,
      "state_string": "failed 1017 expected passes 40 unsupported tests 42 unexpected failures (failure)",
      "workerid": 147
    },
    {
      "builderid": 187,
      "buildid": 183235,
      "buildrequestid": 2150062,
      "complete": true,
      "complete_at": 1633233623,
      "masterid": 2,
      "number": 132,
      "properties": {},
      "results": 2,
      "started_at": 1633233384,
      "state_string": "failed build (failure)",
      "workerid": 147
    },
    {
      "builderid": 187,
      "buildid": 182523,
      "buildrequestid": 2137414,
      "complete": true,
      "complete_at": 1633084186,
      "masterid": 2,
      "number": 75,
      "properties": {},
      "results": 2,
      "started_at": 1633084168,
      "state_string": "failed 'cmake ../llvm.src/llvm ...'",
      "workerid": 147
    },
    {
      "builderid": 187,
      "buildid": 182467,
      "buildrequestid": 2136641,
      "complete": true,
      "complete_at": 1633074223,
      "masterid": 2,
      "number": 71,
      "properties": {},
      "results": 2,
      "started_at": 1633074207,
      "state_string": "failed 'cmake ../llvm.src/llvm ...'",
      "workerid": 147
    },
    {
      "builderid": 187,
      "buildid": 182459,
      "buildrequestid": 2136476,
      "complete": true,
      "complete_at": 1633072962,
      "masterid": 2,
      "number": 70,
      "properties": {},
      "results": 2,
      "started_at": 1633072944,
      "state_string": "failed 'cmake ../llvm.src/llvm ...'",
      "workerid": 147
    },
    {
      "builderid": 187,
      "buildid": 182530,
      "buildrequestid": 2137508,
      "complete": true,
      "complete_at": 1633084875,
      "masterid": 2,
      "number": 76,
      "properties": {},
      "results": 2,
      "started_at": 1633084860,
      "state_string": "failed 'cmake ../llvm.src/llvm ...'",
      "workerid": 147
    },
    {
      "builderid": 187,
      "buildid": 182546,
      "buildrequestid": 2137836,
      "complete": true,
      "complete_at": 1633086630,
      "masterid": 2,
      "number": 78,
      "properties": {},
      "results": 2,
      "started_at": 1633086615,
      "state_string": "failed 'cmake ../llvm.src/llvm ...'",
      "workerid": 147
    },
    {
      "builderid": 187,
      "buildid": 182941,
      "buildrequestid": 2145858,
      "complete": true,
      "complete_at": 1633131135,
      "masterid": 2,
      "number": 115,
      "properties": {},
      "results": 2,
      "started_at": 1633131115,
      "state_string": "failed 'cmake ../llvm.src/llvm ...'",
      "workerid": 147
    },
    {
      "builderid": 187,
      "buildid": 182977,
      "buildrequestid": 2146178,
      "complete": true,
      "complete_at": 1633136708,
      "masterid": 2,
      "number": 118,
      "properties": {},
      "results": 2,
      "started_at": 1633136478,
      "state_string": "failed 'cmake ../llvm.src/llvm ...'",
      "workerid": 147
    },
    {
      "builderid": 187,
      "buildid": 182503,
      "buildrequestid": 2137112,
      "complete": true,
      "complete_at": 1633082125,
      "masterid": 2,
      "number": 73,
      "properties": {},
      "results": 2,
      "started_at": 1633082109,
      "state_string": "failed 'cmake ../llvm.src/llvm ...'",
      "workerid": 147
    },
    {
      "builderid": 187,
      "buildid": 182543,
      "buildrequestid": 2137708,
      "complete": true,
      "complete_at": 1633086584,
      "masterid": 2,
      "number": 77,
      "properties": {},
      "results": 2,
      "started_at": 1633086566,
      "state_string": "failed 'cmake ../llvm.src/llvm ...'",
      "workerid": 147
    },
    {
      "builderid": 187,
      "buildid": 182507,
      "buildrequestid": 2137332,
      "complete": true,
      "complete_at": 1633082505,
      "masterid": 2,
      "number": 74,
      "properties": {},
      "results": 2,
      "started_at": 1633082489,
      "state_string": "failed 'cmake ../llvm.src/llvm ...'",
      "workerid": 147
    },
    {
      "builderid": 187,
      "buildid": 182549,
      "buildrequestid": 2137917,
      "complete": true,
      "complete_at": 1633087354,
      "masterid": 2,
      "number": 79,
      "properties": {},
      "results": 2,
      "started_at": 1633087339,
      "state_string": "failed 'cmake ../llvm.src/llvm ...'",
      "workerid": 147
    },
    {
      "builderid": 187,
      "buildid": 182585,
      "buildrequestid": 2138480,
      "complete": true,
      "complete_at": 1633096474,
      "masterid": 2,
      "number": 82,
      "properties": {},
      "results": 2,
      "started_at": 1633096459,
      "state_string": "failed 'cmake ../llvm.src/llvm ...'",
      "workerid": 147
    },
    {
      "builderid": 187,
      "buildid": 182491,
      "buildrequestid": 2136964,
      "complete": true,
      "complete_at": 1633081306,
      "masterid": 2,
      "number": 72,
      "properties": {},
      "results": 2,
      "started_at": 1633081289,
      "state_string": "failed 'cmake ../llvm.src/llvm ...'",
      "workerid": 147
    },
    {
      "builderid": 187,
      "buildid": 182620,
      "buildrequestid": 2140302,
      "complete": true,
      "complete_at": 1633100617,
      "masterid": 2,
      "number": 87,
      "properties": {},
      "results": 2,
      "started_at": 1633100601,
      "state_string": "failed 'cmake ../llvm.src/llvm ...'",
      "workerid": 147
    },
    {
      "builderid": 187,
      "buildid": 182579,
      "buildrequestid": 2138376,
      "complete": true,
      "complete_at": 1633095463,
      "masterid": 2,
      "number": 81,
      "properties": {},
      "results": 2,
      "started_at": 1633095447,
      "state_string": "failed 'cmake ../llvm.src/llvm ...'",
      "workerid": 147
    },
    {
      "builderid": 187,
      "buildid": 182562,
      "buildrequestid": 2137988,
      "complete": true,
      "complete_at": 1633094589,
      "masterid": 2,
      "number": 80,
      "properties": {},
      "results": 2,
      "started_at": 1633094574,
      "state_string": "failed 'cmake ../llvm.src/llvm ...'",
      "workerid": 147
    },
    {
      "builderid": 187,
      "buildid": 182644,
      "buildrequestid": 2140649,
      "complete": true,
      "complete_at": 1633103364,
      "masterid": 2,
      "number": 88,
      "properties": {},
      "results": 2,
      "started_at": 1633103348,
      "state_string": "failed 'cmake ../llvm.src/llvm ...'",
      "workerid": 147
    },
    {
      "builderid": 187,
      "buildid": 182612,
      "buildrequestid": 2139414,
      "complete": true,
      "complete_at": 1633099925,
      "masterid": 2,
      "number": 85,
      "properties": {},
      "results": 2,
      "started_at": 1633099905,
      "state_string": "failed 'cmake ../llvm.src/llvm ...'",
      "workerid": 147
    },
    {
      "builderid": 187,
      "buildid": 182614,
      "buildrequestid": 2139806,
      "complete": true,
      "complete_at": 1633100357,
      "masterid": 2,
      "number": 86,
      "properties": {},
      "results": 2,
      "started_at": 1633100341,
      "state_string": "'cmake ../llvm.src/llvm ...'",
      "workerid": 147
    },
    {
      "builderid": 187,
      "buildid": 182601,
      "buildrequestid": 2138656,
      "complete": true,
      "complete_at": 1633098909,
      "masterid": 2,
      "number": 84,
      "properties": {},
      "results": 2,
      "started_at": 1633098893,
      "state_string": "failed 'cmake ../llvm.src/llvm ...'",
      "workerid": 147
    },
    {
      "builderid": 187,
      "buildid": 181868,
      "buildrequestid": 2127413,
      "complete": true,
      "complete_at": 1632971168,
      "masterid": 2,
      "number": 6,
      "properties": {},
      "results": 2,
      "started_at": 1632971164,
      "state_string": "'cmake ../llvm.src/llvm ...'",
      "workerid": 147
    },
    {
      "builderid": 187,
      "buildid": 182668,
      "buildrequestid": 2141050,
      "complete": true,
      "complete_at": 1633104681,
      "masterid": 2,
      "number": 90,
      "properties": {},
      "results": 2,
      "started_at": 1633104665,
      "state_string": "failed 'cmake ../llvm.src/llvm ...'",
      "workerid": 147
    },
    {
      "builderid": 187,
      "buildid": 182596,
      "buildrequestid": 2138533,
      "complete": true,
      "complete_at": 1633098646,
      "masterid": 2,
      "number": 83,
      "properties": {},
      "results": 2,
      "started_at": 1633098630,
      "state_string": "failed 'cmake ../llvm.src/llvm ...'",
      "workerid": 147
    },
    {
      "builderid": 187,
      "buildid": 182978,
      "buildrequestid": 2146270,
      "complete": true,
      "complete_at": 1633136724,
      "masterid": 2,
      "number": 119,
      "properties": {},
      "results": 2,
      "started_at": 1633136707,
      "state_string": "failed 'cmake ../llvm.src/llvm ...'",
      "workerid": 147
    },
    {
      "builderid": 187,
      "buildid": 182653,
      "buildrequestid": 2140769,
      "complete": true,
      "complete_at": 1633103713,
      "masterid": 2,
      "number": 89,
      "properties": {},
      "results": 2,
      "started_at": 1633103697,
      "state_string": "'cmake ../llvm.src/llvm ...'",
      "workerid": 147
    },
    {
      "builderid": 187,
      "buildid": 183223,
      "buildrequestid": 2149860,
      "complete": true,
      "complete_at": 1633231525,
      "masterid": 2,
      "number": 128,
      "properties": {},
      "results": 2,
      "started_at": 1633231390,
      "state_string": "failed 985 expected passes 40 unsupported tests 74 unexpected failures (failure)",
      "workerid": 147
    },
    {
      "builderid": 187,
      "buildid": 181870,
      "buildrequestid": 2127414,
      "complete": true,
      "complete_at": 1632971221,
      "masterid": 2,
      "number": 7,
      "properties": {},
      "results": 2,
      "started_at": 1632971209,
      "state_string": "failed 'cmake ../llvm.src/llvm ...'",
      "workerid": 147
    },
    {
      "builderid": 187,
      "buildid": 181896,
      "buildrequestid": 2127415,
      "complete": true,
      "complete_at": 1632975150,
      "masterid": 2,
      "number": 8,
      "properties": {},
      "results": 2,
      "started_at": 1632975138,
      "state_string": "'cmake ../llvm.src/llvm ...'",
      "workerid": 147
    },
    {
      "builderid": 187,
      "buildid": 182375,
      "buildrequestid": 2135223,
      "complete": true,
      "complete_at": 1633042585,
      "masterid": 2,
      "number": 62,
      "properties": {},
      "results": 2,
      "started_at": 1633042572,
      "state_string": "failed 'cmake ../llvm.src/llvm ...'",
      "workerid": 147
    },
    {
      "builderid": 187,
      "buildid": 183243,
      "buildrequestid": 2150275,
      "complete": true,
      "complete_at": 1633235654,
      "masterid": 2,
      "number": 133,
      "properties": {},
      "results": 2,
      "started_at": 1633234989,
      "state_string": "failed 1017 expected passes 40 unsupported tests 42 unexpected failures (failure)",
      "workerid": 147
    },
    {
      "builderid": 187,
      "buildid": 182756,
      "buildrequestid": 2142758,
      "complete": true,
      "complete_at": 1633112779,
      "masterid": 2,
      "number": 100,
      "properties": {},
      "results": 2,
      "started_at": 1633112763,
      "state_string": "failed 'cmake ../llvm.src/llvm ...'",
      "workerid": 147
    },
    {
      "builderid": 187,
      "buildid": 182710,
      "buildrequestid": 2141573,
      "complete": true,
      "complete_at": 1633107829,
      "masterid": 2,
      "number": 94,
      "properties": {},
      "results": 2,
      "started_at": 1633107813,
      "state_string": "failed 'cmake ../llvm.src/llvm ...'",
      "workerid": 147
    },
    {
      "builderid": 187,
      "buildid": 182746,
      "buildrequestid": 2142457,
      "complete": true,
      "complete_at": 1633112327,
      "masterid": 2,
      "number": 98,
      "properties": {},
      "results": 2,
      "started_at": 1633112311,
      "state_string": "failed 'cmake ../llvm.src/llvm ...'",
      "workerid": 147
    },
    {
      "builderid": 187,
      "buildid": 182703,
      "buildrequestid": 2141410,
      "complete": true,
      "complete_at": 1633107583,
      "masterid": 2,
      "number": 93,
      "properties": {},
      "results": 2,
      "started_at": 1633107565,
      "state_string": "failed 'cmake ../llvm.src/llvm ...'",
      "workerid": 147
    },
    {
      "builderid": 187,
      "buildid": 182687,
      "buildrequestid": 2141268,
      "complete": true,
      "complete_at": 1633106348,
      "masterid": 2,
      "number": 92,
      "properties": {},
      "results": 2,
      "started_at": 1633106332,
      "state_string": "failed 'cmake ../llvm.src/llvm ...'",
      "workerid": 147
    },
    {
      "builderid": 187,
      "buildid": 182719,
      "buildrequestid": 2142000,
      "complete": true,
      "complete_at": 1633108678,
      "masterid": 2,
      "number": 95,
      "properties": {},
      "results": 2,
      "started_at": 1633108662,
      "state_string": "failed 'cmake ../llvm.src/llvm ...'",
      "workerid": 147
    },
    {
      "builderid": 187,
      "buildid": 182789,
      "buildrequestid": 2143121,
      "complete": true,
      "complete_at": 1633116225,
      "masterid": 2,
      "number": 102,
      "properties": {},
      "results": 2,
      "started_at": 1633116210,
      "state_string": "'cmake ../llvm.src/llvm ...'",
      "workerid": 147
    },
    {
      "builderid": 187,
      "buildid": 182738,
      "buildrequestid": 2142449,
      "complete": true,
      "complete_at": 1633111053,
      "masterid": 2,
      "number": 97,
      "properties": {},
      "results": 2,
      "started_at": 1633110828,
      "state_string": "failed 'cmake ../llvm.src/llvm ...'",
      "workerid": 147
    },
    {
      "builderid": 187,
      "buildid": 182771,
      "buildrequestid": 2142917,
      "complete": true,
      "complete_at": 1633114150,
      "masterid": 2,
      "number": 101,
      "properties": {},
      "results": 2,
      "started_at": 1633114135,
      "state_string": "failed 'cmake ../llvm.src/llvm ...'",
      "workerid": 147
    },
    {
      "builderid": 187,
      "buildid": 182810,
      "buildrequestid": 2143737,
      "complete": true,
      "complete_at": 1633118336,
      "masterid": 2,
      "number": 104,
      "properties": {},
      "results": 2,
      "started_at": 1633118318,
      "state_string": "failed 'cmake ../llvm.src/llvm ...'",
      "workerid": 147
    },
    {
      "builderid": 187,
      "buildid": 182804,
      "buildrequestid": 2143476,
      "complete": true,
      "complete_at": 1633118218,
      "masterid": 2,
      "number": 103,
      "properties": {},
      "results": 2,
      "started_at": 1633117988,
      "state_string": "failed 'cmake ../llvm.src/llvm ...'",
      "workerid": 147
    },
    {
      "builderid": 187,
      "buildid": 182825,
      "buildrequestid": 2143931,
      "complete": true,
      "complete_at": 1633119102,
      "masterid": 2,
      "number": 105,
      "properties": {},
      "results": 2,
      "started_at": 1633119086,
      "state_string": "failed 'cmake ../llvm.src/llvm ...'",
      "workerid": 147
    },
    {
      "builderid": 187,
      "buildid": 182831,
      "buildrequestid": 2144047,
      "complete": true,
      "complete_at": 1633119343,
      "masterid": 2,
      "number": 106,
      "properties": {},
      "results": 2,
      "started_at": 1633119327,
      "state_string": "failed 'cmake ../llvm.src/llvm ...'",
      "workerid": 147
    },
    {
      "builderid": 187,
      "buildid": 183310,
      "buildrequestid": 2150983,
      "complete": true,
      "complete_at": 1633259423,
      "masterid": 2,
      "number": 139,
      "properties": {},
      "results": 0,
      "started_at": 1633259267,
      "state_string": "build successful",
      "workerid": 147
    },
    {
      "builderid": 187,
      "buildid": 183329,
      "buildrequestid": 2151470,
      "complete": true,
      "complete_at": 1633260945,
      "masterid": 2,
      "number": 140,
      "properties": {},
      "results": 0,
      "started_at": 1633260807,
      "state_string": "build successful",
      "workerid": 147
    },
    {
      "builderid": 187,
      "buildid": 183334,
      "buildrequestid": 2151705,
      "complete": true,
      "complete_at": 1633261229,
      "masterid": 2,
      "number": 141,
      "properties": {},
      "results": 0,
      "started_at": 1633261092,
      "state_string": "build successful",
      "workerid": 147
    },
    {
      "builderid": 187,
      "buildid": 183351,
      "buildrequestid": 2151854,
      "complete": true,
      "complete_at": 1633262681,
      "masterid": 2,
      "number": 142,
      "properties": {},
      "results": 0,
      "started_at": 1633262500,
      "state_string": "build successful",
      "workerid": 147
    },
    {
      "builderid": 187,
      "buildid": 183365,
      "buildrequestid": 2151976,
      "complete": true,
      "complete_at": 1633266577,
      "masterid": 2,
      "number": 143,
      "properties": {},
      "results": 0,
      "started_at": 1633266417,
      "state_string": "build successful",
      "workerid": 147
    },
    {
      "builderid": 187,
      "buildid": 183378,
      "buildrequestid": 2152406,
      "complete": true,
      "complete_at": 1633269419,
      "masterid": 2,
      "number": 144,
      "properties": {},
      "results": 0,
      "started_at": 1633269282,
      "state_string": "build successful",
      "workerid": 147
    },
    {
      "builderid": 187,
      "buildid": 183408,
      "buildrequestid": 2152896,
      "complete": true,
      "complete_at": 1633273101,
      "masterid": 2,
      "number": 146,
      "properties": {},
      "results": 0,
      "started_at": 1633272963,
      "state_string": "build successful",
      "workerid": 147
    },
    {
      "builderid": 187,
      "buildid": 183396,
      "buildrequestid": 2152629,
      "complete": true,
      "complete_at": 1633272257,
      "masterid": 2,
      "number": 145,
      "properties": {},
      "results": 0,
      "started_at": 1633272119,
      "state_string": "build successful",
      "workerid": 147
    },
    {
      "builderid": 187,
      "buildid": 183425,
      "buildrequestid": 2153029,
      "complete": true,
      "complete_at": 1633274993,
      "masterid": 2,
      "number": 147,
      "properties": {},
      "results": 0,
      "started_at": 1633274849,
      "state_string": "build successful",
      "workerid": 147
    },
    {
      "builderid": 187,
      "buildid": 183431,
      "buildrequestid": 2153170,
      "complete": true,
      "complete_at": 1633275465,
      "masterid": 2,
      "number": 148,
      "properties": {},
      "results": 0,
      "started_at": 1633275328,
      "state_string": "build successful",
      "workerid": 147
    },
    {
      "builderid": 187,
      "buildid": 183445,
      "buildrequestid": 2153300,
      "complete": true,
      "complete_at": 1633278087,
      "masterid": 2,
      "number": 149,
      "properties": {},
      "results": 0,
      "started_at": 1633277937,
      "state_string": "build successful",
      "workerid": 147
    },
    {
      "builderid": 187,
      "buildid": 183463,
      "buildrequestid": 2153416,
      "complete": true,
      "complete_at": 1633283058,
      "masterid": 2,
      "number": 150,
      "properties": {},
      "results": 0,
      "started_at": 1633282922,
      "state_string": "build successful",
      "workerid": 147
    },
    {
      "builderid": 187,
      "buildid": 183481,
      "buildrequestid": 2153674,
      "complete": true,
      "complete_at": 1633289558,
      "masterid": 2,
      "number": 152,
      "properties": {},
      "results": 0,
      "started_at": 1633289419,
      "state_string": "build successful",
      "workerid": 147
    },
    {
      "builderid": 187,
      "buildid": 183472,
      "buildrequestid": 2153585,
      "complete": true,
      "complete_at": 1633286092,
      "masterid": 2,
      "number": 151,
      "properties": {},
      "results": 0,
      "started_at": 1633285951,
      "state_string": "build successful",
      "workerid": 147
    }
  ],
  "meta": {
    "total": 152
  }
}